mass_pagure_prs/__init__.py
mass_pagure_prs/local_repo.py
mass_pagure_prs/pagure_fork.py
mass_pagure_prs/prs_generator.py
mass_pagure_prs/selenium_pagure_pr.py
mass_pagure_prs-0.1.dev1.dist-info/DESCRIPTION.rst
mass_pagure_prs-0.1.dev1.dist-info/METADATA
mass_pagure_prs-0.1.dev1.dist-info/RECORD
mass_pagure_prs-0.1.dev1.dist-info/WHEEL
mass_pagure_prs-0.1.dev1.dist-info/metadata.json
mass_pagure_prs-0.1.dev1.dist-info/top_level.txt
pagure_prs/__init__.py
pagure_prs/local_repo.py
pagure_prs/pagure_fork.py
pagure_prs/prs_generator.py
pagure_prs/selenium_pagure_pr.py
test/__init__.py
