Metadata-Version: 2.0
Name: mass-pagure-prs
Version: 0.1.dev1
Summary: A library to do mass Pagure pull requests.
Home-page: UNKNOWN
Author: Iryna Shcherbina
Author-email: shcherbina.iryna@gmail.com
License: MIT
Keywords: pagure mass pr
Platform: UNKNOWN
Classifier: Development Status :: 4 - Beta
Classifier: Intended Audience :: Developers
Classifier: License :: OSI Approved :: MIT License
Classifier: Operating System :: POSIX :: Linux
Classifier: Programming Language :: Python
Classifier: Programming Language :: Python :: 3
Classifier: Topic :: Software Development :: Libraries
Requires-Dist: libpagure
Requires-Dist: selenium
